aliyunsdkververica_inner/__init__.py
aliyunsdkververica_inner/request/__init__.py
aliyunsdkververica_inner/request/v20200501/CreateAlarmContactGroupsRequest.py
aliyunsdkververica_inner/request/v20200501/CreateAlarmContactRequest.py
aliyunsdkververica_inner/request/v20200501/CreateAlarmRuleRequest.py
aliyunsdkververica_inner/request/v20200501/CreateAlarmTemplateRequest.py
aliyunsdkververica_inner/request/v20200501/CreateClusterInfoRequest.py
aliyunsdkververica_inner/request/v20200501/CreateConnectorRequest.py
aliyunsdkververica_inner/request/v20200501/CreateDeploymentRequest.py
aliyunsdkververica_inner/request/v20200501/CreateDeploymentTargetRequest.py
aliyunsdkververica_inner/request/v20200501/CreateFormatRequest.py
aliyunsdkververica_inner/request/v20200501/CreateMemberRequest.py
aliyunsdkververica_inner/request/v20200501/CreateNamespaceRequest.py
aliyunsdkververica_inner/request/v20200501/CreateSavepointRequest.py
aliyunsdkververica_inner/request/v20200501/CreateSessionClusterRequest.py
aliyunsdkververica_inner/request/v20200501/CreateUdfArtifactRequest.py
aliyunsdkververica_inner/request/v20200501/CreateWorkspaceRequest.py
aliyunsdkververica_inner/request/v20200501/DeleteAlarmContactGroupsRequest.py
aliyunsdkververica_inner/request/v20200501/DeleteAlarmContactRequest.py
aliyunsdkververica_inner/request/v20200501/DeleteAlarmRuleRequest.py
aliyunsdkververica_inner/request/v20200501/DeleteAlarmTemplateRequest.py
aliyunsdkververica_inner/request/v20200501/DeleteArtifactRequest.py
aliyunsdkververica_inner/request/v20200501/DeleteClusterInfoRequest.py
aliyunsdkververica_inner/request/v20200501/DeleteConnectorRequest.py
aliyunsdkververica_inner/request/v20200501/DeleteDeploymentRequest.py
aliyunsdkververica_inner/request/v20200501/DeleteDeploymentTargetRequest.py
aliyunsdkververica_inner/request/v20200501/DeleteFormatRequest.py
aliyunsdkververica_inner/request/v20200501/DeleteMemberRequest.py
aliyunsdkververica_inner/request/v20200501/DeleteNamespaceRequest.py
aliyun_python_sdk_ververica_inner-1.0.2.dist-info/LICENSE
aliyun_python_sdk_ververica_inner-1.0.2.dist-info/METADATA
aliyun_python_sdk_ververica_inner-1.0.2.dist-info/WHEEL
aliyun_python_sdk_ververica_inner-1.0.2.dist-info/top_level.txt
aliyun_python_sdk_ververica_inner-1.0.2.dist-info/RECORD
